MANIFEST.in
README.md
pyproject.toml
requirements.txt
setup.py
docs/stefans_scripts/export/90_refresh_materialized_view.sql
docs/stefans_scripts/export/91_maincover.sql
docs/stefans_scripts/export/92_grant_usage.sql
docs/stefans_scripts/export/93_grant_all.sql
docs/stefans_scripts/export/check_coordinate_cover.sql
docs/stefans_scripts/export/check_coordinate_reach_point.sql
docs/stefans_scripts/export/check_coordinate_wastewaternode.sql
docs/stefans_scripts/export/check_length_detail_geometry.sql
docs/stefans_scripts/export/check_length_reach.sql
docs/stefans_scripts/export/sia405_abwasser_2015/01_sia405_abwasser_2015_2_d_tid_generate.sql
docs/stefans_scripts/export/sia405_abwasser_2015/022_sia405_abwasser_2015_2_d_basket_update.sql
docs/stefans_scripts/export/sia405_abwasser_2015/022_vsa_dss_2015_2_d_3122_basket_update.sql
docs/stefans_scripts/export/sia405_abwasser_2015/02_sia405_abwasser_2015_2_d_tid_lookup.sql
docs/stefans_scripts/export/sia405_abwasser_2015/046_sia405_abwasser_2015_2_d_t_key_object_insert_metadata.sql
docs/stefans_scripts/export/sia405_abwasser_2015/050_sia405_abwasser_2015_2.vw_sia405_baseclass_metattribute.sql
docs/stefans_scripts/export/sia405_abwasser_2015/051_sia405_abwasser_2015_2_d_interlisexport2.sql
docs/stefans_scripts/export/sia405_abwasser_2015/052a_sia405_abwasser_2015_2_d_interlisexport2.sql
docs/stefans_scripts/export/sia405_abwasser_2015/create_sia405_abwasser_2015_2_d.count_element_sia405_abwasser.sql
docs/stefans_scripts/export/sia405_abwasser_2015/create_vsa_dss_2015_2_d.count_element_vsa_dss_2015.sql
docs/stefans_scripts/export/vsa_dss_2015/01_vsa_dss_2015_2_d_tid_generate.sql
docs/stefans_scripts/export/vsa_dss_2015/021_vsa_dss_2015_2_d_create_seq_ili2db.sql
docs/stefans_scripts/export/vsa_dss_2015/022_vsa_dss_2015_2_d_basket_update.sql
docs/stefans_scripts/export/vsa_dss_2015/02_vsa_dss_2015_2_d_tid_lookup.sql
docs/stefans_scripts/export/vsa_dss_2015/046_vsa_dss_2015_2_d_t_key_object_insert_metadata.sql
qgepqwat2ili.egg-info/PKG-INFO
qgepqwat2ili.egg-info/SOURCES.txt
qgepqwat2ili.egg-info/dependency_links.txt
qgepqwat2ili.egg-info/requires.txt
qgepqwat2ili.egg-info/top_level.txt
